tsforecasting/__init__.py
tsforecasting/core/__init__.py
tsforecasting/core/base.py
tsforecasting/core/enums.py
tsforecasting/core/exceptions.py
tsforecasting/core/schemas.py
tsforecasting/data/__init__.py
tsforecasting/data/generator.py
tsforecasting/evaluation/__init__.py
tsforecasting/evaluation/engine.py
tsforecasting/evaluation/intervals.py
tsforecasting/evaluation/metrics.py
tsforecasting/models/__init__.py
tsforecasting/models/base.py
tsforecasting/models/forecasters.py
tsforecasting/models/registry.py
tsforecasting/pipeline/__init__.py
tsforecasting/pipeline/forecasting.py
tsforecasting/processing/__init__.py
tsforecasting/processing/feature_selection.py
tsforecasting/processing/processor.py
tsforecasting-1.61.12.dist-info/licenses/LICENSE
tsforecasting-1.61.12.dist-info/METADATA
tsforecasting-1.61.12.dist-info/WHEEL
tsforecasting-1.61.12.dist-info/top_level.txt
tsforecasting-1.61.12.dist-info/RECORD
