Metadata-Version: 2.4
Name: tsforecasting
Version: 1.61.12
Summary: TSForecasting is an automated time series forecasting framework
Home-page: https://github.com/TsLu1s/TSForecasting
Author: Luís Fernando da Silva Santos
Author-email: luisf_ssantos@hotmail.com
License: MIT
Keywords: data science,machine learning,time series forecasting,automated time series,multivariate time series,univariate time series,automated machine learning,automl
Classifier: Intended Audience :: Education
Classifier: Intended Audience :: Developers
Classifier: Intended Audience :: Science/Research
Classifier: Intended Audience :: Customer Service
Classifier: Intended Audience :: Financial and Insurance Industry
Classifier: Intended Audience :: Healthcare Industry
Classifier: Intended Audience :: Telecommunications Industry
Classifier: Topic :: Scientific/Engineering :: Artificial Intelligence
Classifier: Topic :: Scientific/Engineering :: Information Analysis
Classifier: License :: OSI Approved :: MIT License
Classifier: Operating System :: OS Independent
Classifier: Programming Language :: Python :: 3.10
Classifier: Programming Language :: Python :: 3.11
Classifier: Programming Language :: Python :: 3.12
License-File: LICENSE
Requires-Dist: pandas>=1.4.4
Requires-Dist: numpy>=1.23.5
Requires-Dist: python-dateutil>=2.8.2
Requires-Dist: scikit-learn>=1.2.2
Requires-Dist: autogluon>=1.1.0
Requires-Dist: xgboost==2.0.3
Requires-Dist: catboost>=1.2.2
Requires-Dist: tqdm>=4.65.2
Dynamic: author
Dynamic: author-email
Dynamic: classifier
Dynamic: description
Dynamic: description-content-type
Dynamic: home-page
Dynamic: keywords
Dynamic: license
Dynamic: license-file
Dynamic: requires-dist
Dynamic: summary
